rowantree/game/service/sdk/__init__.py
rowantree/game/service/sdk/service.py
rowantree/game/service/sdk/commands/__init__.py
rowantree/game/service/sdk/commands/abstract_command.py
rowantree/game/service/sdk/commands/action_queue_process.py
rowantree/game/service/sdk/commands/health_get.py
rowantree/game/service/sdk/commands/merchant_transforms_perform.py
rowantree/game/service/sdk/commands/world_get.py
rowantree/game/service/sdk/commands/user/__init__.py
rowantree/game/service/sdk/commands/user/active_get.py
rowantree/game/service/sdk/commands/user/active_set.py
rowantree/game/service/sdk/commands/user/create.py
rowantree/game/service/sdk/commands/user/delete.py
rowantree/game/service/sdk/commands/user/feature_active_get.py
rowantree/game/service/sdk/commands/user/features_get.py
rowantree/game/service/sdk/commands/user/income_get.py
rowantree/game/service/sdk/commands/user/income_set.py
rowantree/game/service/sdk/commands/user/merchant_transforms_get.py
rowantree/game/service/sdk/commands/user/population_get.py
rowantree/game/service/sdk/commands/user/state_get.py
rowantree/game/service/sdk/commands/user/stores_get.py
rowantree/game/service/sdk/commands/user/transport.py
rowantree/game/service/sdk/contracts/__init__.py
rowantree/game/service/sdk/contracts/exceeded_retry_count_error.py
rowantree/game/service/sdk/contracts/request_failure_error.py
rowantree/game/service/sdk/contracts/request_verb.py
rowantree/game/service/sdk/contracts/user_active_status.py
rowantree/game/service/sdk/contracts/dto/__init__.py
rowantree/game/service/sdk/contracts/dto/command_options.py
rowantree/game/service/sdk/contracts/dto/request_status_codes.py
rowantree/game/service/sdk/contracts/dto/world_status.py
rowantree/game/service/sdk/contracts/dto/wrapped_request.py
rowantree/game/service/sdk/contracts/requests/__init__.py
rowantree/game/service/sdk/contracts/requests/merchant_transform.py
rowantree/game/service/sdk/contracts/requests/user/__init__.py
rowantree.game.service.sdk-0.27.0.dist-info/LICENSE
rowantree.game.service.sdk-0.27.0.dist-info/METADATA
rowantree.game.service.sdk-0.27.0.dist-info/WHEEL
rowantree.game.service.sdk-0.27.0.dist-info/top_level.txt
rowantree.game.service.sdk-0.27.0.dist-info/RECORD
